csuayyy
