Metadata-Version: 2.1
Name: csuayyy
Version: 0.0.6
Summary: CLI for easily interfacing with Berkeley CSUA
Home-page: UNKNOWN
Author: Armaan Goel
Author-email: armaangoel78@gmail.com
License: UNKNOWN
Platform: UNKNOWN
Requires-Python: >=3.6
